audiotoolbox/__init__.py
audiotoolbox/audio_functions.py
audiotoolbox/audiotoolbox.py
audiotoolbox/auditory_filter.py
audiotoolbox/din_iso_226.py
audiotoolbox/io.py
audiotoolbox/scales.py
audiotoolbox/filter/__init__.py
audiotoolbox/filter/brickwall_filt.py
audiotoolbox/filter/butterworth_filt.py
audiotoolbox/filter/filter.py
audiotoolbox/filter/freq_weighting.py
audiotoolbox/filter/gammatone_filt.py
audiotoolbox/filter/bank/__init__.py
audiotoolbox/filter/bank/default_banks.py
audiotoolbox/filter/bank/filterbank.py
audiotoolbox/filter/bank/octave_bank.py
audiotoolbox/oaudio/__init__.py
audiotoolbox/oaudio/base_signal.py
audiotoolbox/oaudio/freqdomain_signal.py
audiotoolbox/oaudio/signal.py
audiotoolbox/oaudio/stats.py
audiotoolbox/oaudio/time_frequency.py
audiotoolbox/oaudio/signal_mixins/__init__.py
audiotoolbox/oaudio/signal_mixins/analysis.py
audiotoolbox/oaudio/signal_mixins/filtering.py
audiotoolbox/oaudio/signal_mixins/generation.py
audiotoolbox/oaudio/signal_mixins/io.py
audiotoolbox/oaudio/signal_mixins/modification.py
audiotoolbox/scales/__init__.py
audiotoolbox/scales/bark.py
audiotoolbox/scales/erb.py
audiotoolbox/scales/octave.py
audiotoolbox-0.75.dist-info/licenses/LICENSE
audiotoolbox-0.75.dist-info/METADATA
audiotoolbox-0.75.dist-info/WHEEL
audiotoolbox-0.75.dist-info/top_level.txt
audiotoolbox-0.75.dist-info/RECORD
