Metadata-Version: 2.4
Name: audiotoolbox
Version: 0.75
Summary: Toolbox for generating and working with audio signals
Author-email: Jörg Encke <encke.joerg@gmail.com>
Project-URL: Homepage, https://jencke.github.io/audiotoolbox/index.html
Classifier: Programming Language :: Python :: 3
Classifier: License :: OSI Approved :: GNU General Public License v3 (GPLv3)
Classifier: Topic :: Multimedia :: Sound/Audio
Classifier: Topic :: Scientific/Engineering
Requires-Python: >=3.10
License-File: LICENSE
Requires-Dist: numpy
Requires-Dist: scipy
Requires-Dist: matplotlib
Requires-Dist: soundfile
Requires-Dist: sounddevice
Requires-Dist: resampy
Provides-Extra: dev
Requires-Dist: pytest; extra == "dev"
Requires-Dist: coverage; extra == "dev"
Requires-Dist: pytest-cov; extra == "dev"
Provides-Extra: docs
Requires-Dist: sphinx; extra == "docs"
Requires-Dist: sphinx-rtd-theme; extra == "docs"
Requires-Dist: matplotlib; extra == "docs"
Dynamic: license-file
